{
    "Clients": {
      "clients": [
        "image1",
        "image2"
      ]
    },
    "Reaches": {
      "Down": 1000,
      "Hosp": 86,
      "Comm": 37
    },
    "Header": {

        "title": "Promoting Rational Anti-Microbial Medicines Use",
        "paragraph": "The mobile application that assist healthcare providers in the provision of empirical therapy for infectious diseases in real-time."

    },
    "About": {
        "paragraph": "We are a healthcare solutions company based in Nigeria. We remain committed towards contributing to Nigeria’s cause of achieving the targets of Sustainable Development Goal 3: Good health and well-being by providing healthcare professionals with expanded access to quality healthcare point-of-reference resources and guidance to facilitate infection diagnosis, treatment and control.",
        "Why": [
            "Improve clinical outcome",
            "Promotes rational use of Antimicrobials",
            "Reduce treatment cost to patient"
        ],
        "Why2": [
            "Limits spread of Antimicrobial resistance",
            "Reduce Antimicrobial consumption"
        ]
    },
    "Services": [{
            "icon": "fa fa-wordpress",
            "name": "Lorem ipsum dolor",
            "text": "Lorem ipsum dolor sit amet, consectetur adipiscing elit. Duis sed dapibus leo nec ornare diam sedasd commodo nibh ante facilisis bibendum dolor feugiat at."
        },
        {
            "icon": "fa fa-cart-arrow-down",
            "name": "Consectetur adipiscing",
            "text": "Lorem ipsum dolor sit amet, consectetur adipiscing elit. Duis sed dapibus leo nec ornare diam sedasd commodo nibh ante facilisis bibendum dolor feugiat at."
        },
        {
            "icon": "fa fa-cloud-download",
            "name": "Lorem ipsum dolor",
            "text": "Lorem ipsum dolor sit amet, consectetur adipiscing elit. Duis sed dapibus leo nec ornare diam sedasd commodo nibh ante facilisis bibendum dolor feugiat at."
        }
    ],
    "Testimonials": [{
            "img": "img/waje.jpg",
            "text": "\"MicrobicPro simplifies the tasks of initiating emperical therapy by providing easy access to current guidelines and antibiograms.\"",
            "name": "Wale Agbaje"
        }
    ],
    "Team": [{
            "img": "img/ayo.jpg",
            "name": "Hassan Diyaolu",
            "job": "CEO/Co-founder"
        },
        {
            "img": "img/const.jpg",
            "name": "Constance Edesiri",
            "job": "Brand/Marketing Manager"
        }
    ],
    "Contact": {
        "address": "2 olusesi close carwash abeokuta",
        "phone": "+234 809171441",
        "email": "info@microbicpro.com",
        "facebook": "fb.com",
        "twitter": "twitter.com",
        "youtube": "youtube.com"
    },
    "Features": [{
            "icon": "fa fa-list-alt",
            "title": "Giudelines",
            "text": "National infectious disease treatment guidelines."
        },
        {
            "icon": "fa fa-drug",
            "title": "Antibiograms",
            "text": "general and specific location antibiogram data."
        },
        {
            "icon": "fa fa-battery",
            "title": "Efficacy Rankings",
            "text": "Automatic Sample based Antibiotics efficacy ranking."
        },
        {
            "icon": "fa fa-gear",
            "title": "Tools",
            "text": "All other MicrobicPro tools."
        }
    ]
}